dime_xai/__init__.py
dime_xai/__main__.py
dime_xai/dime_xai.py
dime_xai/cli/__init__.py
dime_xai/cli/dime_cli.py
dime_xai/core/__init__.py
dime_xai/core/custom_dime_explainer.py
dime_xai/core/dime_core.py
dime_xai/core/dime_explainer.py
dime_xai/core/rasa_dime_explainer.py
dime_xai/server/__init__.py
dime_xai/server/dime_server.py
dime_xai/server/dime_api/__init__.py
dime_xai/server/dime_api/routes.py
dime_xai/server/dime_api/static/dime_gray.png
dime_xai/server/dime_api/utils/__init__.py
dime_xai/server/dime_api/utils/server_configs.py
dime_xai/server/dime_api/utils/statistics.py
dime_xai/server/frontend/asset-manifest.json
dime_xai/server/frontend/index.html
dime_xai/server/frontend/manifest.json
dime_xai/server/frontend/res/images/android-chrome-192x192.png
dime_xai/server/frontend/res/images/android-chrome-512x512.png
dime_xai/server/frontend/res/images/apple-touch-icon.png
dime_xai/server/frontend/res/images/dime-favicon.png
dime_xai/server/frontend/res/images/dime_xai_dark.png
dime_xai/server/frontend/res/images/dime_xai_light.png
dime_xai/server/frontend/res/images/dime_xai_steel.png
dime_xai/server/frontend/res/images/favicon-16x16.png
dime_xai/server/frontend/res/images/favicon-32x32.png
dime_xai/server/frontend/res/images/favicon.ico
dime_xai/server/frontend/res/images/manifest.json
dime_xai/server/frontend/res/scripts/bootstrap.min.js
dime_xai/server/frontend/res/styles/app_styles.css
dime_xai/server/frontend/res/styles/bootstrap.min.css
dime_xai/server/frontend/res/styles/ghost.css
dime_xai/server/frontend/static/css/main.fbd77886.css
dime_xai/server/frontend/static/css/main.fbd77886.css.map
dime_xai/server/frontend/static/js/787.0f148dca.chunk.js
dime_xai/server/frontend/static/js/787.0f148dca.chunk.js.map
dime_xai/server/frontend/static/js/main.330b5d10.js
dime_xai/server/frontend/static/js/main.330b5d10.js.LICENSE.txt
dime_xai/server/frontend/static/js/main.330b5d10.js.map
dime_xai/server/frontend/static/media/dimeGray.99c075f2b43327a0161f.png
dime_xai-1.2.1.dist-info/LICENSE
dime_xai-1.2.1.dist-info/METADATA
dime_xai-1.2.1.dist-info/WHEEL
dime_xai-1.2.1.dist-info/entry_points.txt
dime_xai-1.2.1.dist-info/top_level.txt
dime_xai-1.2.1.dist-info/RECORD
